pythomata/__init__.py
pythomata/__version__.py
pythomata/_internal_utils.py
pythomata/alphabets.py
pythomata/core.py
pythomata/simulator.py
pythomata/utils.py
pythomata/impl/__init__.py
pythomata/impl/simple.py
pythomata/impl/symbolic.py
pythomata-0.3.2.dist-info/LICENSE
pythomata-0.3.2.dist-info/METADATA
pythomata-0.3.2.dist-info/WHEEL
pythomata-0.3.2.dist-info/top_level.txt
pythomata-0.3.2.dist-info/RECORD
