Metadata-Version: 2.1
Name: pythomata
Version: 0.3.2
Summary: A Python package for automata theory.
Home-page: https://github.com/whitemech/pythomata.git
Author: Marco Favorito, Francesco Fuggitti
Author-email: marco.favorito@gmail.com, francesco.fuggitti@gmail.com
License: LGPL-3.0-or-later
Keywords: pythomata
Platform: UNKNOWN
Classifier: Development Status :: 2 - Pre-Alpha
Classifier: Intended Audience :: Developers
Classifier: License :: OSI Approved :: GNU Lesser General Public License v3 or later (LGPLv3+)
Classifier: Natural Language :: English
Classifier: Programming Language :: Python :: 3
Classifier: Programming Language :: Python :: 3.6
Classifier: Programming Language :: Python :: 3.7
Classifier: Programming Language :: Python :: 3.8
